WuyunZhishikuDisanBufen/README.md
WuyunZhishikuDisanBufen/__init__.py
WuyunZhishikuDisanBufen/__main__.py
WuyunZhishikuDisanBufen/file.epub
WuyunZhishikuDisanBufen/index.html
WuyunZhishikuDisanBufen/css/__init__.py
WuyunZhishikuDisanBufen/css/annotations.css
WuyunZhishikuDisanBufen/css/main.css
WuyunZhishikuDisanBufen/css/normalize.css
WuyunZhishikuDisanBufen/css/popup.css
WuyunZhishikuDisanBufen/font/__init__.py
WuyunZhishikuDisanBufen/font/fontello.eot
WuyunZhishikuDisanBufen/font/fontello.svg
WuyunZhishikuDisanBufen/font/fontello.ttf
WuyunZhishikuDisanBufen/font/fontello.woff
WuyunZhishikuDisanBufen/img/__init__.py
WuyunZhishikuDisanBufen/img/annotator-glyph-sprite.png
WuyunZhishikuDisanBufen/img/annotator-icon-sprite.png
WuyunZhishikuDisanBufen/img/apple-touch-icon.png
WuyunZhishikuDisanBufen/img/cancelfullscreen.png
WuyunZhishikuDisanBufen/img/close.png
WuyunZhishikuDisanBufen/img/fullscreen.png
WuyunZhishikuDisanBufen/img/loader.gif
WuyunZhishikuDisanBufen/img/menu-icon.png
WuyunZhishikuDisanBufen/img/save.png
WuyunZhishikuDisanBufen/img/saved.png
WuyunZhishikuDisanBufen/img/settings-s.png
WuyunZhishikuDisanBufen/img/settings.png
WuyunZhishikuDisanBufen/img/star.png
WuyunZhishikuDisanBufen/js/__init__.py
WuyunZhishikuDisanBufen/js/epub.js
WuyunZhishikuDisanBufen/js/epub.min.js
WuyunZhishikuDisanBufen/js/epub.min.map
WuyunZhishikuDisanBufen/js/hooks.min.js
WuyunZhishikuDisanBufen/js/hooks.min.map
WuyunZhishikuDisanBufen/js/reader.js
WuyunZhishikuDisanBufen/js/reader.js.map
WuyunZhishikuDisanBufen/js/reader.min.js
WuyunZhishikuDisanBufen/js/reader.min.map
WuyunZhishikuDisanBufen/js/hooks/__init__.py
WuyunZhishikuDisanBufen/js/hooks/extensions/__init__.py
WuyunZhishikuDisanBufen/js/hooks/extensions/highlight.js
WuyunZhishikuDisanBufen/js/libs/__init__.py
WuyunZhishikuDisanBufen/js/libs/jquery.min.js
WuyunZhishikuDisanBufen/js/libs/localforage.min.js
WuyunZhishikuDisanBufen/js/libs/screenfull.js
WuyunZhishikuDisanBufen/js/libs/screenfull.min.js
wuyun_zhishiku_disan_bufen-2024.3.5.0.dist-info/METADATA
wuyun_zhishiku_disan_bufen-2024.3.5.0.dist-info/WHEEL
wuyun_zhishiku_disan_bufen-2024.3.5.0.dist-info/entry_points.txt
wuyun_zhishiku_disan_bufen-2024.3.5.0.dist-info/top_level.txt
wuyun_zhishiku_disan_bufen-2024.3.5.0.dist-info/RECORD
